uopython/__init__.py
uopython/sdk/__init__.py
uopython/sdk/animations.py
uopython/sdk/art.py
uopython/sdk/ascii_font.py
uopython/sdk/bodies.py
uopython/sdk/file_index.py
uopython/sdk/gumps.py
uopython/sdk/hues.py
uopython/sdk/map.py
uopython/sdk/radarcol.py
uopython/sdk/render.py
uopython/sdk/skills.py
uopython/sdk/tile_data.py
uopython/sdk/tile_matrix.py
uopython/sdk/utils.py
uopython/sdk/verdata.py
uopython/settings/__init__.py
uopython/settings/settings.py
uopython-0.2.0.dist-info/LICENSE
uopython-0.2.0.dist-info/METADATA
uopython-0.2.0.dist-info/WHEEL
uopython-0.2.0.dist-info/top_level.txt
uopython-0.2.0.dist-info/RECORD
