Metadata-Version: 2.2
Name: UOPython
Version: 0.2.0
Summary: UOPython - Extract information and images from the UO client files. New Fork from jackuolls ultima-py
Home-page: https://github.com/NerdyGamers/UOPython
Author: JBob
Author-email: thatdudejbob@gmail.com
License: Beerware
Classifier: Programming Language :: Python :: 3
Classifier: Programming Language :: Python :: 3.7
Classifier: Programming Language :: Python :: 3.8
Classifier: Programming Language :: Python :: 3.9
Classifier: Programming Language :: Python :: 3.10
Classifier: Operating System :: OS Independent
Classifier: License :: Freeware
Classifier: Development Status :: 4 - Beta
License-File: LICENSE
Requires-Dist: Pillow
Requires-Dist: imageio
Requires-Dist: numpy
Requires-Dist: matplotlib
Dynamic: author
Dynamic: author-email
Dynamic: classifier
Dynamic: description
Dynamic: description-content-type
Dynamic: home-page
Dynamic: license
Dynamic: requires-dist
Dynamic: summary
